Metadata-Version: 1.1
Name: cpf
Version: 2.1
Summary: Gera e checa CPFs de acordo com o padrão brasileiro.
Home-page: UNKNOWN
Author: pedrokp
Author-email: pedrokp@protonmail.com
License: MIT
Keywords: cpf
Platform: UNKNOWN
Classifier: Development Status :: 5 - Production/Stable
Classifier: Intended Audience :: Education
Classifier: Operating System :: Microsoft :: Windows :: Windows 10
Classifier: License :: OSI Approved :: MIT License
Classifier: Programming Language :: Python :: 3
